pymarkdownsax/__init__.py
pymarkdownsax/pymarkdownsax.py
pymarkdownsax/tests/__init__.py
pymarkdownsax/tests/test_all.py
pymarkdownsax-0.0.1.dist-info/METADATA
pymarkdownsax-0.0.1.dist-info/WHEEL
pymarkdownsax-0.0.1.dist-info/top_level.txt
pymarkdownsax-0.0.1.dist-info/RECORD
