Metadata-Version: 2.1
Name: pymarkdownsax
Version: 0.0.1
Summary: MarkDown processing for python
Home-page: https://github.com/rumca-js/pymarkdownsax
Author: Piotr Zielinski
Author-email: rozbujnik@gmail.com
License: UNKNOWN
Platform: UNKNOWN
Classifier: Programming Language :: Python :: 3
Classifier: License :: OSI Approved :: MIT License
Classifier: Operating System :: OS Independent
Requires-Python: >=3.6
